{
  "configurations": [
    {
      "name": "x64-Debug",
      "generator": "Ninja",
      "configurationType": "Debug",
      "inheritEnvironments": [ "msvc_x64_x64" ],
      "buildRoot": "${projectDir}\\build\\${name}",
      "installRoot": "${projectDir}\\build\\install\\${name}",
      "cmakeCommandArgs": "",
      "buildCommandArgs": "",
      "ctestCommandArgs": "",
      "variables": [
        {
          "name": "QT_DIR",
          "value": "C:/Qt/5.15.1/msvc2019_64",
          "type": "PATH"
        },
        {
          "name": "VCPKG_TARGET_TRIPLET",
          "value": "x64-windows-static-md-v141",
          "type": "STRING"
        },
        {
          "name": "CMAKE_CXX_FLAGS",
          "value": "/DWIN32 /D_WINDOWS /W4 /GR /EHsc",
          "type": "STRING"
        },
        {
          "name": "Qt5_DIR",
          "value": "C:/Qt/5.15.1/msvc2019_64",
          "type": "PATH"
        }
      ]
    }
  ]
}